{
    "afg": "Afghanistan",
    "zaf": "Afrique du Sud",
    "alb": "Albanie",
    "dza": "Alg\u00e9rie",
    "deu": "Allemagne",
    "and": "Andorre",
    "ago": "Angola",
    "aia": "Anguilla",
    "atg": "Antigua-et-Barbuda",
    "ant": "Antilles n\u00e9erlandaises",
    "sau": "Arabie saoudite",
    "arg": "Argentine",
    "arm": "Arm\u00e9nie",
    "abw": "Aruba",
    "aus": "Australie",
    "aut": "Autriche",
    "aze": "Azerba\u00efdjan",
    "bhs": "Bahamas",
    "bhr": "Bahre\u00efn",
    "bgd": "Bangladesh",
    "brb": "Barbade",
    "blr": "B\u00e9larus",
    "bel": "Belgique",
    "blz": "Belize",
    "ben": "B\u00e9nin",
    "bmu": "Bermudes",
    "btn": "Bhoutan",
    "bol": "Bolivie",
    "bih": "Bosnie-Herz\u00e9govine",
    "bwa": "Botswana",
    "bra": "Br\u00e9sil",
    "brn": "Brunei Darussalam",
    "bgr": "Bulgarie",
    "bfa": "Burkina Faso",
    "bdi": "Burundi",
    "cpv": "Cabo Verde",
    "khm": "Cambodge",
    "cmr": "Cameroun",
    "can": "Canada",
    "chl": "Chili",
    "chn": "Chine",
    "cyp": "Chypre",
    "pse": "Cisjordanie et bande de Gaza",
    "col": "Colombie",
    "com": "Comores",
    "cog": "Congo",
    "kor": "Cor\u00e9e",
    "cri": "Costa Rica",
    "civ": "C\u00f4te d'Ivoire",
    "hrv": "Croatie",
    "cub": "Cuba",
    "dnk": "Danemark",
    "dji": "Djibouti",
    "dma": "Dominique",
    "egy": "\u00c9gypte",
    "slv": "El Salvador",
    "are": "\u00c9mirats arabes unis",
    "ecu": "\u00c9quateur",
    "mkd": "ERYM",
    "eri": "\u00c9rythr\u00e9e",
    "esp": "Espagne",
    "est": "Estonie",
    "usa": "\u00c9tats-Unis",
    "eth": "\u00c9thiopie",
    "fji": "Fidji",
    "fin": "Finlande",
    "fra": "France",
    "gab": "Gabon",
    "gmb": "Gambie",
    "geo": "G\u00e9orgie",
    "gha": "Ghana",
    "grc": "Gr\u00e8ce",
    "grd": "Grenade",
    "gum": "Guam",
    "gtm": "Guatemala",
    "ggy": "Guernesey",
    "gin": "Guin\u00e9e",
    "gnq": "Guin\u00e9e \u00e9quatoriale",
    "gnb": "Guin\u00e9e-Bissau",
    "guy": "Guyana",
    "hti": "Ha\u00efti",
    "hnd": "Honduras",
    "hkg": "Hong Kong, Chine",
    "hun": "Hongrie",
    "bvt": "Ile Bouvet",
    "cxr": "Ile Christmas",
    "nfk": "Ile Norfolk",
    "imn": "Ile de Man",
    "cym": "Iles Ca\u00efmanes",
    "cok": "Iles Cook",
    "flk": "Iles Falkland (Malouines)",
    "sgs": "Iles G\u00e9orgie du Sud et Sandwich du Sud",
    "hmd": "Iles Heard et McDonald",
    "mnp": "Iles Mariannes du Nord",
    "mhl": "Iles Marshall",
    "slb": "Iles Salomon",
    "tca": "Iles Turques et Ca\u00efques",
    "vgb": "Iles Vierges britanniques",
    "vir": "Iles Vierges des \u00c9tats-Unis",
    "umi": "Iles mineures \u00e9loign\u00e9es des \u00c9tats-Unis",
    "ind": "Inde",
    "idn": "Indon\u00e9sie",
    "irn": "Iran",
    "irq": "Iraq",
    "irl": "Irlande",
    "isl": "Islande",
    "isr": "Isra\u00ebl",
    "ita": "Italie",
    "jam": "Jama\u00efque",
    "jpn": "Japon",
    "jey": "Jersey",
    "jor": "Jordanie",
    "kaz": "Kazakhstan",
    "ken": "Kenya",
    "kgz": "Kirghizistan",
    "kir": "Kiribati",
    "kos": "Kosovo",
    "kwt": "Kowe\u00eft",
    "lso": "Lesotho",
    "lva": "Lettonie",
    "lbn": "Liban",
    "lbr": "Lib\u00e9ria",
    "lby": "Libye",
    "lie": "Liechtenstein",
    "ltu": "Lituanie",
    "lux": "Luxembourg",
    "mac": "Macao, Chine",
    "mdg": "Madagascar",
    "mys": "Malaisie",
    "mwi": "Malawi",
    "mdv": "Maldives",
    "mli": "Mali",
    "mlt": "Malte",
    "mar": "Maroc",
    "mus": "Maurice",
    "mrt": "Mauritanie",
    "myt": "Mayotte",
    "mex": "Mexique",
    "fsm": "Micron\u00e9sie",
    "mda": "Moldova",
    "mco": "Monaco",
    "mng": "Mongolie",
    "mne": "Mont\u00e9n\u00e9gro",
    "msr": "Montserrat",
    "moz": "Mozambique",
    "mmr": "Myanmar",
    "nam": "Namibie",
    "nru": "Nauru",
    "npl": "N\u00e9pal",
    "nic": "Nicaragua",
    "ner": "Niger",
    "nga": "Nig\u00e9ria",
    "niu": "Niue",
    "nor": "Norv\u00e8ge",
    "ncl": "Nouvelle-Cal\u00e9donie",
    "nzl": "Nouvelle-Z\u00e9lande",
    "omn": "Oman",
    "uga": "Ouganda",
    "uzb": "Ouzb\u00e9kistan",
    "pak": "Pakistan",
    "plw": "Palaos",
    "pan": "Panama",
    "png": "Papouasie-Nouvelle-Guin\u00e9e",
    "pry": "Paraguay",
    "nld": "Pays-Bas",
    "per": "P\u00e9rou",
    "phl": "Philippines",
    "pcn": "Pitcairn",
    "pol": "Pologne",
    "pyf": "Polyn\u00e9sie fran\u00e7aise",
    "pri": "Porto Rico",
    "prt": "Portugal",
    "qat": "Qatar",
    "cod": "RDC",
    "lao": "RDP lao",
    "caf": "R\u00e9publique centrafricaine",
    "dom": "R\u00e9publique dominicaine",
    "svk": "R\u00e9publique slovaque",
    "cze": "R\u00e9publique tch\u00e8que",
    "rou": "Roumanie",
    "gbr": "Royaume-Uni",
    "prk": "RPDC",
    "rus": "Russie",
    "rwa": "Rwanda",
    "esh": "Sahara occidental",
    "kna": "Saint-Kitts-et-Nevis",
    "smr": "Saint-Marin",
    "vct": "Saint-Vincent-et-les-Grenadines",
    "shn": "Sainte-H\u00e9l\u00e8ne",
    "lca": "Sainte-Lucie",
    "wsm": "Samoa",
    "asm": "Samoa am\u00e9ricaines",
    "stp": "Sao Tom\u00e9-et-Principe",
    "sen": "S\u00e9n\u00e9gal",
    "srb": "Serbie",
    "syc": "Seychelles",
    "sle": "Sierra Leone",
    "sgp": "Singapour",
    "svn": "Slov\u00e9nie",
    "som": "Somalie",
    "sdn": "Soudan",
    "ssd": "Soudan du Sud",
    "lka": "Sri Lanka",
    "swe": "Su\u00e8de",
    "che": "Suisse",
    "sur": "Suriname",
    "swz": "Swaziland",
    "syr": "Syrie",
    "atf": "TAAF",
    "tjk": "Tadjikistan",
    "twn": "Taipei chinois",
    "tza": "Tanzanie",
    "tcd": "Tchad",
    "iot": "Territoire britannique de l\u2019oc\u00e9an Indien",
    "tha": "Tha\u00eflande",
    "tls": "Timor-Leste",
    "tgo": "Togo",
    "tkl": "Tok\u00e9laou",
    "ton": "Tonga",
    "tto": "Trinit\u00e9-et-Tobago",
    "tun": "Tunisie",
    "tkm": "Turkm\u00e9nistan",
    "tur": "Turquie",
    "tuv": "Tuvalu",
    "ukr": "Ukraine",
    "ury": "Uruguay",
    "vut": "Vanuatu",
    "ven": "Venezuela",
    "vnm": "Viet Nam",
    "wlf": "Wallis-et-Futuna",
    "yem": "Y\u00e9men",
    "zmb": "Zambie",
    "zwe": "Zimbabwe"
}
