{
    "downloadAsPDF": "按PDF格式下载",
    "countryProfile": "查看国家简介",
    "addCountry": "添加国家",
    "Home": "更多主题",
    "Compare": "对照",
    "and": "和",
    "aboutEmail": "电子邮件",
    "aboutRelatedWebsite": "载有补充信息的网站",
    "aboutRelatedRead": "阅读该出版物",
    "aboutRelatedPublication": "相关出版物",
    "aboutRelatedPublications": "Related Publications",
    "aboutDataSource": "数据来源",
    "aboutFacebook": "脸书",
    "aboutTwitter": "推特",
    "aboutEmbed": "嵌入",
    "full_screen": "全屏",
    "feedback": "反馈",
    "def_button": "定义",
    "dload_button": "下载数据",
    "download_text": "按Excel文件下载该指标。",
    "about_08": "Collaborative model",
    "about_button": "About this site",
    "about_data_button": "数据来源/关于",
    "changeView": "改变视图",
    "feedback_send": "Send us your feedback.",
    "languages": "语言",
    "noDataAvailable": "没有数据",
    "ranking": {
        "country": "国家",
        "helpText": "把光标放在表格标题上获取详细的指标定义，点击表格标题在某个选择的指标上进行国家排序",
        "selectText": "选择指标"
    },
    "template": {
        "1": "趋势",
        "6": "排名",
        "7": "地图"
    },
    "share_button": "分享/嵌入",
    "titleDisplaySelectInstruction": "从下拉菜单选择指标",
    "mapZoomIn": "放大",
    "mapZoomOut": "缩小",
    "mapBubbleSize": "泡泡大小",
    "min": "最小值",
    "max": "最大值",
    "share_by_email": "Share by Email",
    "thousand": "千",
    "million": "百万",
    "billion": "十亿",
    "trillion": "万亿",
    "month": {
        "1": "January",
        "2": "February",
        "3": "March",
        "4": "April",
        "5": "May",
        "6": "June",
        "7": "July",
        "8": "August",
        "9": "September",
        "10": "October",
        "11": "November",
        "12": "December"
    },
    "projections": "预测",
    "SelectMap": "从地图选择国家"
}
