{
    "RedBlue10": [
        "#67001F",
        "#B2182B",
        "#D6604D",
        "#F4A582",
        "#FDDBC7",
        "#D1E5F0",
        "#92C5DE",
        "#4393C3",
        "#2166AC",
        "#053061"
    ],
    "Blue9OLD": [
        "#F7FBFF",
        "#DEEBF7",
        "#C6DBEF",
        "#9ECAE1",
        "#6BAED6",
        "#4292C6",
        "#2171B5",
        "#08519C",
        "#08306B"
    ],
    "Blue8": [
        "#bfe1f1",
        "#9ac8de",
        "#74aecc",
        "#4f95ba",
        "#2a7ca8",
        "#07537b",
        "#074262",
        "#161d21"
    ],
    "Brown9": [
        "#FFF5EB",
        "#FEE6CE",
        "#FDD0A2",
        "#FDAE6B",
        "#FD8D3C",
        "#F16913",
        "#D94801",
        "#A63603",
        "#7F2704"
    ],
    "Purple9": [
        "#FCFBFD",
        "#EFEDF5",
        "#DADAEB",
        "#BCBDDC",
        "#9E9AC8",
        "#807DBA",
        "#6A51A3",
        "#54278F",
        "#3F007D"
    ],
    "Red9": [
        "#FFF5F0",
        "#FEE0D2",
        "#FCBBA1",
        "#FC9272",
        "#FB6A4A",
        "#EF3B2C",
        "#CB181D",
        "#A50F15",
        "#67000D"
    ],
    "Green8": [
        "#a1e867",
        "#8ecc5b",
        "#8bc859",
        "#6b9945",
        "#5c833b",
        "#4c6e31",
        "#3d5827",
        "#2f421d"
    ]
}
